src/aurora_models/__init__.py
src/aurora_models/datatypes.py
src/aurora_models/scripts/__init__.py
src/aurora_models/scripts/example_chat_completion.py
src/aurora_models/scripts/example_text_completion.py
src/aurora_models/scripts/multimodal_example_chat_completion.py
src/aurora_models/scripts/multimodal_example_text_completion.py
src/aurora_models/sl_aurora_01KG/__init__.py
src/aurora_models/sl_aurora_01KG/api/__init__.py
src/aurora_models/sl_aurora_01KG/api/args.py
src/aurora_models/sl_aurora_01KG/api/chat_format.py
src/aurora_models/sl_aurora_01KG/api/tokenizer.py
src/aurora_models/sl_aurora_01KG/api/tool_utils.py
src/aurora_models/sl_aurora_01KG/reference_impl/__init__.py
src/aurora_models/sl_aurora_01KG/reference_impl/generation.py
src/aurora_models/sl_aurora_01KG/reference_impl/model.py
src/aurora_models/sl_aurora_01KG/reference_impl/multimodal/__init__.py
src/aurora_models/sl_aurora_01KG/reference_impl/multimodal/encoder_utils.py
src/aurora_models/sl_aurora_01KG/reference_impl/multimodal/image_transform.py
src/aurora_models/sl_aurora_01KG/reference_impl/multimodal/model.py
src/aurora_models/sl_aurora_01KG/reference_impl/multimodal/utils.py
src/aurora_models/sl_aurora_01KG/tests/api/test_generation.py
src/aurora_models/sl_aurora_01KG/tests/api/test_tokenizer.py
src/aurora_models/sl_aurora_01KG/tests/api/test_tool_utils.py
src/models/__init__.py
src/models/datatypes.py
src/models/scripts/__init__.py
src/models/scripts/example_chat_completion.py
src/models/scripts/example_text_completion.py
src/models/scripts/multimodal_example_chat_completion.py
src/models/scripts/multimodal_example_text_completion.py
src/models/sl_aurora_01KG/__init__.py
src/models/sl_aurora_01KG/api/__init__.py
src/models/sl_aurora_01KG/api/args.py
src/models/sl_aurora_01KG/api/chat_format.py
src/models/sl_aurora_01KG/api/tokenizer.py
src/models/sl_aurora_01KG/api/tool_utils.py
src/models/sl_aurora_01KG/reference_impl/__init__.py
src/models/sl_aurora_01KG/reference_impl/generation.py
aurora_models-0.1.1.dist-info/METADATA
aurora_models-0.1.1.dist-info/WHEEL
aurora_models-0.1.1.dist-info/entry_points.txt
aurora_models-0.1.1.dist-info/top_level.txt
aurora_models-0.1.1.dist-info/RECORD
