Metadata-Version: 2.4
Name: aurora_models
Version: 0.1.1
Summary: Aurora models
Author-email: Scrumlab Aurora <aurora-oss@scrumlab.com.br>
Project-URL: Homepage, https://github.com/scrum-lab/aurora-models
Requires-Python: >=3.10
Requires-Dist: PyYAML
Requires-Dist: jinja2
Requires-Dist: tiktoken
Requires-Dist: pydantic>=2
Requires-Dist: Pillow
Provides-Extra: dev
Requires-Dist: pytest; extra == "dev"
Requires-Dist: black; extra == "dev"
Requires-Dist: isort; extra == "dev"
Requires-Dist: mypy; extra == "dev"
Requires-Dist: ruff; extra == "dev"
Provides-Extra: torch
Requires-Dist: torch; extra == "torch"
Requires-Dist: fairscale; extra == "torch"
Requires-Dist: fire; extra == "torch"
Requires-Dist: blobfile; extra == "torch"
